JwtEncoder/JWKS.py
JwtEncoder/JwtEncoder.py
JwtEncoder/__init__.py
JwtEncoder-21.8.30.dist-info/LICENSE.txt
JwtEncoder-21.8.30.dist-info/METADATA
JwtEncoder-21.8.30.dist-info/WHEEL
JwtEncoder-21.8.30.dist-info/top_level.txt
JwtEncoder-21.8.30.dist-info/RECORD
