Metadata-Version: 2.1
Name: JwtEncoder
Version: 21.8.30
Summary: JWT authentication plugin for Bottle
Home-page: https://github.com/Glocktober/JwtEncoder
Author: gunville
Author-email: rk13088@yahoo.com
License: UNKNOWN
Project-URL: repo, https://github.com/Glocktober/JwtEncoder
Project-URL: overview, https://github.com/Glocktober/JwtEncoder/blob/main/README.md
Keywords: 'jwt oidc jwks'
Platform: UNKNOWN
Classifier: Programming Language :: Python :: 3
Classifier: License :: OSI Approved :: MIT License
Classifier: Operating System :: OS Independent
Classifier: Framework :: Bottle
Requires-Python: >=3.6
License-File: LICENSE.txt
Requires-Dist: cryptography (>=3.0)
Requires-Dist: Requests (>=2.26.0)
Requires-Dist: PyJWT (>=2.1.0)
